MANIFEST.in
README.md
requirements.in
setup.py
kfp/__init__.py
kfp/init_test.py
kfp/cli/__init__.py
kfp/cli/__main__.py
kfp/cli/cli.py
kfp/cli/cli_test.py
kfp/cli/compile_.py
kfp/cli/compile_test.py
kfp/cli/component.py
kfp/cli/component_test.py
kfp/cli/diagnose_me_cli.py
kfp/cli/dsl.py
kfp/cli/experiment.py
kfp/cli/output.py
kfp/cli/pipeline.py
kfp/cli/recurring_run.py
kfp/cli/run.py
kfp/cli/diagnose_me/__init__.py
kfp/cli/diagnose_me/dev_env.py
kfp/cli/diagnose_me/dev_env_test.py
kfp/cli/diagnose_me/gcp.py
kfp/cli/diagnose_me/gcp_test.py
kfp/cli/diagnose_me/kubernetes_cluster.py
kfp/cli/diagnose_me/kubernetes_cluster_test.py
kfp/cli/diagnose_me/utility.py
kfp/cli/diagnose_me/utility_test.py
kfp/cli/utils/__init__.py
kfp/cli/utils/aliased_plurals_group.py
kfp/cli/utils/aliased_plurals_group_test.py
kfp/cli/utils/deprecated_alias_group.py
kfp/cli/utils/deprecated_alias_group_test.py
kfp/cli/utils/parsing.py
kfp/cli/utils/parsing_test.py
kfp/client/__init__.py
kfp/client/auth.py
kfp/client/auth_test.py
kfp/client/client.py
kfp/client/client_test.py
kfp/client/set_volume_credentials.py
kfp/client/set_volume_credentials_test.py
kfp/client/token_credentials_base.py
kfp/client/token_credentials_base_test.py
kfp/compiler/__init__.py
kfp/compiler/compiler.py
kfp/compiler/compiler_test.py
kfp/compiler/compiler_utils.py
kfp/compiler/compiler_utils_test.py
kfp/compiler/pipeline_spec_builder.py
kfp/compiler/pipeline_spec_builder_test.py
kfp/compiler/read_write_test.py
kfp/components/__init__.py
kfp/components/load_yaml_utilities.py
kfp/components/load_yaml_utilities_test.py
kfp/deprecated/__init__.py
kfp/deprecated/__main__.py
kfp/deprecated/_auth.py
kfp/deprecated/_client.py
kfp/deprecated/_config.py
kfp/deprecated/_local_client.py
kfp/deprecated/_runners.py
kfp/deprecated/aws.py
kfp/deprecated/azure.py
kfp/deprecated/gcp.py
kfp/deprecated/onprem.py
kfp/deprecated/auth/__init__.py
kfp/deprecated/auth/_satvolumecredentials.py
kfp/deprecated/auth/_tokencredentialsbase.py
kfp_leinao.egg-info/PKG-INFO
kfp_leinao.egg-info/SOURCES.txt
kfp_leinao.egg-info/dependency_links.txt
kfp_leinao.egg-info/entry_points.txt
kfp_leinao.egg-info/requires.txt
kfp_leinao.egg-info/top_level.txt
