Metadata-Version: 2.1
Name: kfp-leinao
Version: 2.4.0
Summary: Kubeflow Pipelines SDK
Home-page: https://github.com/kubeflow/pipelines
Author: The Kubeflow Authors
Project-URL: Documentation, https://kubeflow-pipelines.readthedocs.io/en/stable/
Project-URL: Bug Tracker, https://github.com/kubeflow/pipelines/issues
Project-URL: Source, https://github.com/kubeflow/pipelines/tree/master/sdk
Project-URL: Changelog, https://github.com/kubeflow/pipelines/blob/master/sdk/RELEASE.md
Classifier: Intended Audience :: Developers
Classifier: Intended Audience :: Education
Classifier: Intended Audience :: Science/Research
Classifier: License :: OSI Approved :: Apache Software License
Classifier: Programming Language :: Python :: 3
Classifier: Programming Language :: Python :: 3.7
Classifier: Programming Language :: Python :: 3.8
Classifier: Programming Language :: Python :: 3.9
Classifier: Programming Language :: Python :: 3.10
Classifier: Programming Language :: Python :: 3.11
Classifier: Programming Language :: Python :: 3.12
Classifier: Topic :: Scientific/Engineering
Classifier: Topic :: Scientific/Engineering :: Artificial Intelligence
Classifier: Topic :: Software Development
Classifier: Topic :: Software Development :: Libraries
Classifier: Topic :: Software Development :: Libraries :: Python Modules
Requires-Python: >=3.7.0,<3.13.0
Requires-Dist: click<9,>=8.0.0
Requires-Dist: docstring-parser<1,>=0.7.3
Requires-Dist: google-api-core!=2.0.*,!=2.1.*,!=2.2.*,!=2.3.0,<3.0.0dev,>=1.31.5
Requires-Dist: google-auth<3,>=1.6.1
Requires-Dist: google-cloud-storage<3,>=2.2.1
Requires-Dist: kfp-pipeline-spec==0.2.2
Requires-Dist: kfp-server-api<2.1.0,>=2.0.0
Requires-Dist: kubernetes<27,>=8.0.0
Requires-Dist: protobuf<4,>=3.13.0
Requires-Dist: PyYAML<7,>=5.3
Requires-Dist: requests-toolbelt<1,>=0.8.0
Requires-Dist: tabulate<1,>=0.8.6
Requires-Dist: urllib3<2.0.0
Requires-Dist: typing-extensions<5,>=3.7.4; python_version < "3.9"
Provides-Extra: all
Requires-Dist: docker; extra == "all"
Requires-Dist: kfp-kubernetes-leinao<2; extra == "all"
Provides-Extra: kubernetes
Requires-Dist: kfp-kubernetes-leinao<2; extra == "kubernetes"
